uncrumpled_xpybutil-0.0.1.data/data/share/doc/xpybutil/COPYING
uncrumpled_xpybutil-0.0.1.data/data/share/doc/xpybutil/README
uncrumpled_xpybutil-0.0.1.dist-info/DESCRIPTION.rst
uncrumpled_xpybutil-0.0.1.dist-info/METADATA
uncrumpled_xpybutil-0.0.1.dist-info/RECORD
uncrumpled_xpybutil-0.0.1.dist-info/WHEEL
uncrumpled_xpybutil-0.0.1.dist-info/metadata.json
uncrumpled_xpybutil-0.0.1.dist-info/top_level.txt
xpybutil/__init__.py
xpybutil/cursor.py
xpybutil/event.py
xpybutil/ewmh.py
xpybutil/font.py
xpybutil/icccm.py
xpybutil/image.py
xpybutil/keybind.py
xpybutil/keysymdef.py
xpybutil/motif.py
xpybutil/mousebind.py
xpybutil/rect.py
xpybutil/render.py
xpybutil/util.py
xpybutil/window.py
xpybutil/xinerama.py
