Metadata-Version: 2.0
Name: uncrumpled-xpybutil
Version: 0.0.1
Summary: An incomplete xcb-util port plus some extras
Home-page: http://pytyle.com
Author: Andrew Gallant
Author-email: andrew@pytyle.com
License: WTFPL
Platform: POSIX
